waylake/__init__.py
waylake/utils.py
waylake_utils-0.1.10.dist-info/METADATA
waylake_utils-0.1.10.dist-info/WHEEL
waylake_utils-0.1.10.dist-info/top_level.txt
waylake_utils-0.1.10.dist-info/RECORD
