Metadata-Version: 2.1
Name: waylake-utils
Version: 0.1.10
Summary: Custom logging utility
Author: waylake
Author-email: plmokn7034soo@icloud.com
